buzzy/index.html
buzzy/log.py
buzzy/path.py
buzzy/args.py
buzzy/__init__.py
buzzy/render.py
buzzy/packages/__init__.py
buzzy/packages/markdown/blockparser.py
buzzy/packages/markdown/inlinepatterns.py
buzzy/packages/markdown/preprocessors.py
buzzy/packages/markdown/postprocessors.py
buzzy/packages/markdown/util.py
buzzy/packages/markdown/treeprocessors.py
buzzy/packages/markdown/odict.py
buzzy/packages/markdown/__version__.py
buzzy/packages/markdown/__init__.py
buzzy/packages/markdown/__main__.py
buzzy/packages/markdown/blockprocessors.py
buzzy/packages/markdown/serializers.py
buzzy/packages/markdown/extensions/meta.py
buzzy/packages/markdown/extensions/tables.py
buzzy/packages/markdown/extensions/smart_strong.py
buzzy/packages/markdown/extensions/nl2br.py
buzzy/packages/markdown/extensions/wikilinks.py
buzzy/packages/markdown/extensions/def_list.py
buzzy/packages/markdown/extensions/attr_list.py
buzzy/packages/markdown/extensions/__init__.py
buzzy/packages/markdown/extensions/fenced_code.py
buzzy/packages/markdown/extensions/codehilite.py
buzzy/packages/markdown/extensions/extra.py
buzzy/packages/markdown/extensions/admonition.py
buzzy/packages/markdown/extensions/toc.py
buzzy/packages/markdown/extensions/headerid.py
buzzy/packages/markdown/extensions/sane_lists.py
buzzy/packages/markdown/extensions/footnotes.py
buzzy/packages/markdown/extensions/abbr.py
buzzy/templates/blog/main.js
buzzy/templates/blog/main.py
buzzy/templates/blog/posts/second.html
buzzy/templates/blog/posts/first.html
buzzy/templates/blog/libs/jquery.pjax.js
buzzy/templates/blog/libs/jquery-1.9.1.min.js
buzzy/templates/blog/libs/bootstrap/js/bootstrap.js
buzzy/templates/blog/libs/bootstrap/js/bootstrap.min.js
buzzy/templates/blog/libs/bootstrap/img/glyphicons-halflings-white.png
buzzy/templates/blog/libs/bootstrap/img/glyphicons-halflings.png
buzzy/templates/blog/libs/bootstrap/css/bootstrap-responsive.css
buzzy-0.5.2.dist-info/DESCRIPTION.rst
buzzy-0.5.2.dist-info/RECORD
buzzy-0.5.2.dist-info/METADATA
buzzy-0.5.2.dist-info/WHEEL
buzzy-0.5.2.dist-info/pydist.json
buzzy-0.5.2.dist-info/top_level.txt
