Metadata-Version: 2.0
Name: buzzy
Version: 0.5.2
Summary: Static site generator
Home-page: http://buzzy.xando.org
Author: Sebastian Pawluś
Author-email: sebastian.pawlus@gmail.com
License: BSD
Keywords: website static generator
Platform: UNKNOWN
Classifier: Development Status :: 4 - Beta
Classifier: Environment :: Web Environment
Classifier: License :: OSI Approved :: BSD License
Classifier: Programming Language :: Python :: 2.7
Requires-Dist: watchdog (==0.7.1)
